mlflashtune/__init__.py
mlflashtune/cli/__init__.py
mlflashtune/cli/__main__.py
mlflashtune/cli/main.py
mlflashtune/core/__init__.py
mlflashtune/core/config.py
mlflashtune/core/data.py
mlflashtune/core/models.py
mlflashtune/core/optimizer.py
mlflashtune/core/output.py
mlflashtune/web/__init__.py
mlflashtune/web/analysis/__init__.py
mlflashtune/web/analysis/analyzer.py
mlflashtune/web/interactive/__init__.py
mlflashtune/web/interactive/app.py
mlflashtune-0.0.4.dist-info/licenses/LICENSE
mlflashtune-0.0.4.dist-info/METADATA
mlflashtune-0.0.4.dist-info/WHEEL
mlflashtune-0.0.4.dist-info/entry_points.txt
mlflashtune-0.0.4.dist-info/top_level.txt
mlflashtune-0.0.4.dist-info/RECORD
