Metadata-Version: 2.4
Name: mlflashtune
Version: 0.0.4
Summary: ML Flash Tune - Advanced ensemble optimization system for LightGBM hyperparameter tuning
Author-email: MLFlashTune Development Team <mlflashtune-dev@example.com>
License-Expression: MIT
Project-URL: Homepage, https://github.com/example/mlflashtune
Project-URL: Documentation, https://github.com/example/mlflashtune/docs
Project-URL: Repository, https://github.com/example/mlflashtune
Project-URL: Issues, https://github.com/example/mlflashtune/issues
Classifier: Development Status :: 4 - Beta
Classifier: Intended Audience :: Developers
Classifier: Intended Audience :: Science/Research
Classifier: Operating System :: OS Independent
Classifier: Programming Language :: Python :: 3
Classifier: Programming Language :: Python :: 3.8
Classifier: Programming Language :: Python :: 3.9
Classifier: Programming Language :: Python :: 3.10
Classifier: Programming Language :: Python :: 3.11
Classifier: Topic :: Scientific/Engineering :: Artificial Intelligence
Requires-Python: >=3.8
License-File: LICENSE
Requires-Dist: ax-platform>=0.3.0
Requires-Dist: sqlalchemy<2.0.0
Requires-Dist: lightgbm<5.0.0,>=3.3.0
Requires-Dist: polars>=0.18.0
Requires-Dist: pandas<3.0.0,>=1.5.0
Requires-Dist: numpy>=1.21.0
Requires-Dist: scikit-learn<2.0.0,>=1.1.0
Requires-Dist: matplotlib>=3.5.0
Requires-Dist: joblib>=1.1.0
Requires-Dist: flask<4.0.0,>=2.0.0
Requires-Dist: plotly<7.0.0,>=5.0.0
Requires-Dist: seaborn>=0.11.0
Requires-Dist: pyarrow>=17.0.0
Requires-Dist: keyring>=25.5.0
Requires-Dist: build>=1.2.2.post1
Provides-Extra: dev
Requires-Dist: pytest>=7.0.0; extra == "dev"
Requires-Dist: pytest-cov>=3.0.0; extra == "dev"
Requires-Dist: coverage>=6.0.0; extra == "dev"
Requires-Dist: black>=22.0.0; extra == "dev"
Requires-Dist: flake8>=5.0.0; extra == "dev"
Requires-Dist: mypy>=0.991; extra == "dev"
Requires-Dist: sphinx>=5.0.0; extra == "dev"
Requires-Dist: sphinx-rtd-theme>=1.0.0; extra == "dev"
Requires-Dist: jupyter>=1.0.0; extra == "dev"
Requires-Dist: ipython>=8.0.0; extra == "dev"
Dynamic: license-file
